setup.py
linkeddataframe/__init__.py
linkeddataframe/ldf.py
linkeddataframe.egg-info/PKG-INFO
linkeddataframe.egg-info/SOURCES.txt
linkeddataframe.egg-info/dependency_links.txt
linkeddataframe.egg-info/requires.txt
linkeddataframe.egg-info/top_level.txt
linkeddataframe/tests/__init__.py
linkeddataframe/tests/test_ldf.py