Metadata-Version: 1.0
Name: linkeddataframe
Version: 0.0.1
Summary: Subclass of DataFrame which allows linking to other DataFrames.
Home-page: https://github.com/pbsag/linkeddataframe
Author: Peter Kucirek
Author-email: pkucirek@pbworld.com
License: UNKNOWN
Platform: any
